fl_common/__init__.py
fl_common/config.py
fl_common/networks.py
fl_common/utils.py
fl_common-1.1.3.dist-info/licenses/LICENSE
fl_common-1.1.3.dist-info/METADATA
fl_common-1.1.3.dist-info/WHEEL
fl_common-1.1.3.dist-info/top_level.txt
fl_common-1.1.3.dist-info/RECORD
