Metadata-Version: 2.4
Name: fl-common
Version: 1.1.3
Summary: This is a package for the commons library used across servers and clients.
Author-email: Litaotao <2835876784@qq.com>
License: MIT License
License-File: LICENSE
Dynamic: license-file
